LICENSE
MANIFEST.in
NOTICE
README.rst
requirements.txt
setup.py
test-requirements.txt
tox.ini
hp_sdn_client.egg-info/PKG-INFO
hp_sdn_client.egg-info/SOURCES.txt
hp_sdn_client.egg-info/dependency_links.txt
hp_sdn_client.egg-info/not-zip-safe
hp_sdn_client.egg-info/requires.txt
hp_sdn_client.egg-info/top_level.txt
hpsdnclient/__init__.py
hpsdnclient/api.py
hpsdnclient/apibase.py
hpsdnclient/auth.py
hpsdnclient/core.py
hpsdnclient/datatypes.py
hpsdnclient/error.py
hpsdnclient/net.py
hpsdnclient/of.py
hpsdnclient/rest.py
hpsdnclient/utils.py
hpsdnclient/version.py
hpsdnclient/tests/__init__.py
hpsdnclient/tests/base.py
hpsdnclient/tests/data.py
hpsdnclient/tests/functional/__init__.py
hpsdnclient/tests/functional/test_coremixin.py
hpsdnclient/tests/functional/test_netmixin.py
hpsdnclient/tests/functional/test_ofmixin.py
hpsdnclient/tests/unit/__init__.py
hpsdnclient/tests/unit/test_apibase.py
hpsdnclient/tests/unit/test_auth.py
hpsdnclient/tests/unit/test_client.py
hpsdnclient/tests/unit/test_datatypes.py
hpsdnclient/tests/unit/test_errors.py
hpsdnclient/tests/unit/test_rest.py
hpsdnclient/tests/unit/test_utils.py