Metadata-Version: 1.1
Name: hp-sdn-client
Version: 1.1.1
Summary: A python library to make interacting with theSDN Controller REST API easy
Home-page: https://github.com/dave-tucker/hp-sdn-client
Author: Dave Tucker, Hewlett-Packard Development Company, L.P
Author-email: dave.j.tucker@hp.com
License: Apache License, Version 2.0
Keywords: hp,sdn,rest,api
Platform: UNKNOWN
Classifier: Environment :: Console
Classifier: Development Status :: 4 - Beta
Classifier: Intended Audience :: Developers
Classifier: Intended Audience :: System Administrators
Classifier: License :: OSI Approved :: Apache Software License
Classifier: Programming Language :: Python
Classifier: Natural Language :: English
Classifier: Operating System :: OS Independent
Classifier: Topic :: Software Development :: Libraries :: Python Modules
